relaxedjson/__init__.py
relaxedjson-1.0.1.dist-info/DESCRIPTION.rst
relaxedjson-1.0.1.dist-info/METADATA
relaxedjson-1.0.1.dist-info/RECORD
relaxedjson-1.0.1.dist-info/WHEEL
relaxedjson-1.0.1.dist-info/metadata.json
relaxedjson-1.0.1.dist-info/top_level.txt
